[
  {
    "scientific_name": "Achillea milleflorium",
    "common_name": "Yarrow",
    "lifeform": "grnd covr",
    "category": "GROUND COVERS",
    "comments": "perennial,  summer semi-deciduous",
    "ca_native": true,
    "origin": "California Native",
    "fire_rating": "Fire-Resistant",
    "recommendation": "",
    "pyrophytic": false
  },
  {
    "scientific_name": "Ajuga reptans",
    "common_name": "Carpet bugleweed",
    "lifeform": "grnd cover",
    "category": "GROUND COVERS",
    "comments": "perennial,  can be invasive",
    "ca_native": false,
    "origin": "Europe",
    "fire_rating": "Fire-Resistant",
    "recommendation": "",
    "pyrophytic": false
  },
  {
    "scientific_name": "Armeria maritima ssp californica",
    "common_name": "California Sea Pink  (Thrift)",
    "lifeform": "grnd covr",
    "category": "GROUND COVERS",
    "comments": "evergreen",
    "ca_native": true,
    "origin": "California Native",
    "fire_rating": "Fire-Resistant",
    "recommendation": "",
    "pyrophytic": false
  },
  {
    "scientific_name": "Cerastium tomentosum",
    "common_name": "Snow-in-Summer",
    "lifeform": "grnd cover",
    "category": "GROUND COVERS",
    "comments": "perennial,  can be invasive",
    "ca_native": false,
    "origin": "Europe",
    "fire_rating": "Fire-Resistant",
    "recommendation": "",
    "pyrophytic": false
  },
  {
    "scientific_name": "Coprosma kirkii",
    "common_name": "Creeping Coprosma",
    "lifeform": "grnd cover, shrub",
    "category": "GROUND COVERS",
    "comments": "evergreen, deciduous, can be invasive",
    "ca_native": false,
    "origin": "Australia, So. Pacific",
    "fire_rating": "Fire-Resistant",
    "recommendation": "",
    "pyrophytic": false
  },
  {
    "scientific_name": "Delosperma hybrids",
    "common_name": "Trailing Iceplant",
    "lifeform": "grnd cover",
    "category": "GROUND COVERS",
    "comments": "succulent",
    "ca_native": false,
    "origin": "So. & E. Africa",
    "fire_rating": "Fire-Resistant",
    "recommendation": "",
    "pyrophytic": false
  },
  {
    "scientific_name": "Drosanthemum sp.",
    "common_name": "Rosea Ice Plant",
    "lifeform": "grnd cover",
    "category": "GROUND COVERS",
    "comments": "succulent",
    "ca_native": false,
    "origin": "So. Africa",
    "fire_rating": "Fire-Resistant",
    "recommendation": "",
    "pyrophytic": false
  },
  {
    "scientific_name": "Eounymus Fortunei coloratus",
    "common_name": "Winter Creeper",
    "lifeform": "grnd cover, vine",
    "category": "GROUND COVERS",
    "comments": "can be invasive",
    "ca_native": false,
    "origin": "E. Asia",
    "fire_rating": "Fire-Resistant",
    "recommendation": "",
    "pyrophytic": false
  },
  {
    "scientific_name": "Erigeron glaucus",
    "common_name": "Beach Aster (Seaside Fleabane)",
    "lifeform": "grnd cover",
    "category": "GROUND COVERS",
    "comments": "perennial",
    "ca_native": true,
    "origin": "California Native",
    "fire_rating": "Fire-Resistant",
    "recommendation": "",
    "pyrophytic": false
  },
  {
    "scientific_name": "Festuca spp",
    "common_name": "California Fescue",
    "lifeform": "grnd covr",
    "category": "GROUND COVERS",
    "comments": "perennial, summer dormant",
    "ca_native": false,
    "origin": "X  (4 native to EB Hills)",
    "fire_rating": "Fire-Resistant",
    "recommendation": "",
    "pyrophytic": false
  },
  {
    "scientific_name": "Fragaria chiloensis/Fragaria vesca",
    "common_name": "Wild or Coast Strawberry\n(Woodland strawberry)",
    "lifeform": "grnd covr",
    "category": "GROUND COVERS",
    "comments": "evergreen",
    "ca_native": true,
    "origin": "California Native",
    "fire_rating": "Fire-Resistant",
    "recommendation": "",
    "pyrophytic": false
  },
  {
    "scientific_name": "Iberis sempervirens",
    "common_name": "Evergreen Candytuft",
    "lifeform": "grnd cover",
    "category": "GROUND COVERS",
    "comments": "evergreen",
    "ca_native": false,
    "origin": "Europe",
    "fire_rating": "Fire-Resistant",
    "recommendation": "",
    "pyrophytic": false
  },
  {
    "scientific_name": "Lampranthus spp.",
    "common_name": "Bush Ice Plant",
    "lifeform": "grnd cover",
    "category": "GROUND COVERS",
    "comments": "succulent",
    "ca_native": false,
    "origin": "So. Africa",
    "fire_rating": "Fire-Resistant",
    "recommendation": "",
    "pyrophytic": false
  },
  {
    "scientific_name": "Liriope gigantea",
    "common_name": "Giant Turf Lily",
    "lifeform": "grnd cover, shrub",
    "category": "GROUND COVERS",
    "comments": "evergreen",
    "ca_native": false,
    "origin": "S.E.Asia",
    "fire_rating": "Fire-Resistant",
    "recommendation": "",
    "pyrophytic": false
  },
  {
    "scientific_name": "Pelargonium peltatum",
    "common_name": "Ivy Geranium",
    "lifeform": "grnd cover, shrub",
    "category": "GROUND COVERS",
    "comments": "succulent",
    "ca_native": false,
    "origin": "So. Africa",
    "fire_rating": "Fire-Resistant",
    "recommendation": "",
    "pyrophytic": false
  },
  {
    "scientific_name": "Phyla nodiflora",
    "common_name": "Common Lippia",
    "lifeform": "grnd cover",
    "category": "GROUND COVERS",
    "comments": "perennial",
    "ca_native": true,
    "origin": "California Native",
    "fire_rating": "Fire-Resistant",
    "recommendation": "",
    "pyrophytic": false
  },
  {
    "scientific_name": "Potentilla anserina, Potentilla rivalis",
    "common_name": "Silverweed/Brook River Cinquefoil",
    "lifeform": "grnd cover",
    "category": "GROUND COVERS",
    "comments": "perennial",
    "ca_native": false,
    "origin": "X  (4 native to EB Hills)",
    "fire_rating": "Fire-Resistant",
    "recommendation": "",
    "pyrophytic": false
  },
  {
    "scientific_name": "Drymocallis glandulosa",
    "common_name": "Sticky Cinquefoil (Woodbeauty)",
    "lifeform": "grnd cover",
    "category": "GROUND COVERS",
    "comments": "perennial,  winter deciduous",
    "ca_native": true,
    "origin": "California Native",
    "fire_rating": "Fire-Resistant",
    "recommendation": "",
    "pyrophytic": false
  },
  {
    "scientific_name": "Salvia spp.",
    "common_name": "Sage",
    "lifeform": "grnd covr",
    "category": "GROUND COVERS",
    "comments": "perennial",
    "ca_native": false,
    "origin": "X  (2 native to EB Hills)",
    "fire_rating": "Fire-Resistant",
    "recommendation": "",
    "pyrophytic": false
  },
  {
    "scientific_name": "Santolina virens",
    "common_name": "Green Lavender Cotton",
    "lifeform": "grnd cover, shrub",
    "category": "GROUND COVERS",
    "comments": "perennial",
    "ca_native": false,
    "origin": "Mediterranean",
    "fire_rating": "Fire-Resistant",
    "recommendation": "",
    "pyrophytic": false
  },
  {
    "scientific_name": "Sedum spp.",
    "common_name": "Stonecrop",
    "lifeform": "grnd cover",
    "category": "GROUND COVERS",
    "comments": "perennial succulent",
    "ca_native": false,
    "origin": "X  (21 native to CA)",
    "fire_rating": "Fire-Resistant",
    "recommendation": "",
    "pyrophytic": false
  },
  {
    "scientific_name": "Senecio serpens, mandralisce, vitalis",
    "common_name": "Blue chalksticks",
    "lifeform": "grnd cover",
    "category": "GROUND COVERS",
    "comments": "succulent",
    "ca_native": false,
    "origin": "So Africa",
    "fire_rating": "Fire-Resistant",
    "recommendation": "",
    "pyrophytic": false
  },
  {
    "scientific_name": "Sisyrinchium bellum,\nS. californicum",
    "common_name": "Blue-eyed Grass/ Yellow-eyed Grass",
    "lifeform": "grnd covr",
    "category": "GROUND COVERS",
    "comments": "perennial",
    "ca_native": false,
    "origin": "X  (1 native to EB Hills)",
    "fire_rating": "Fire-Resistant",
    "recommendation": "",
    "pyrophytic": false
  },
  {
    "scientific_name": "Thymus praecox arcticus",
    "common_name": "Creeping Thyme",
    "lifeform": "grnd cover",
    "category": "GROUND COVERS",
    "comments": "evergreen, can be invasive",
    "ca_native": false,
    "origin": "Europe",
    "fire_rating": "Fire-Resistant",
    "recommendation": "",
    "pyrophytic": false
  },
  {
    "scientific_name": "Verbena peruviana",
    "common_name": "Perennial Verbena (Vervain)",
    "lifeform": "grnd cover",
    "category": "GROUND COVERS",
    "comments": "evergreen",
    "ca_native": false,
    "origin": "So. America",
    "fire_rating": "Fire-Resistant",
    "recommendation": "",
    "pyrophytic": false
  },
  {
    "scientific_name": "Achillea tomentosa",
    "common_name": "Woolly Yarrow",
    "lifeform": "Perennial, \ngrnd cover",
    "category": "PERENNIALS",
    "comments": "evergreen",
    "ca_native": false,
    "origin": "Eurasia",
    "fire_rating": "Fire-Resistant",
    "recommendation": "",
    "pyrophytic": false
  },
  {
    "scientific_name": "Aeonium spp.",
    "common_name": "Aeonium",
    "lifeform": "Perennial",
    "category": "PERENNIALS",
    "comments": "succulent",
    "ca_native": false,
    "origin": "Canary Islands, E. Africa",
    "fire_rating": "Fire-Resistant",
    "recommendation": "",
    "pyrophytic": false
  },
  {
    "scientific_name": "Agapanthus spp.",
    "common_name": "Lily-of-the-Nile",
    "lifeform": "Perennial",
    "category": "PERENNIALS",
    "comments": "evergreen",
    "ca_native": false,
    "origin": "So. Africa",
    "fire_rating": "Fire-Resistant",
    "recommendation": "",
    "pyrophytic": false
  },
  {
    "scientific_name": "Agave spp.",
    "common_name": "Agave",
    "lifeform": "Perennial",
    "category": "PERENNIALS",
    "comments": "succulent",
    "ca_native": false,
    "origin": "Mexico, So. America",
    "fire_rating": "Fire-Resistant",
    "recommendation": "",
    "pyrophytic": false
  },
  {
    "scientific_name": "Aloe spp.",
    "common_name": "Aloe",
    "lifeform": "Perennial",
    "category": "PERENNIALS",
    "comments": "succulent",
    "ca_native": false,
    "origin": "So. Africa, Indian Ocean",
    "fire_rating": "Fire-Resistant",
    "recommendation": "",
    "pyrophytic": false
  },
  {
    "scientific_name": "Aquilegia formosa",
    "common_name": "Western Columbine",
    "lifeform": "Perennial",
    "category": "PERENNIALS",
    "comments": "winter deciduous",
    "ca_native": true,
    "origin": "California Native",
    "fire_rating": "Fire-Resistant",
    "recommendation": "",
    "pyrophytic": false
  },
  {
    "scientific_name": "Asarum caudatum",
    "common_name": "Wild Ginger",
    "lifeform": "Perennial, shrub",
    "category": "PERENNIALS",
    "comments": "evergreen",
    "ca_native": true,
    "origin": "California Native",
    "fire_rating": "Fire-Resistant",
    "recommendation": "",
    "pyrophytic": false
  },
  {
    "scientific_name": "Bergenia spp.",
    "common_name": "Bergenia \n(Elephant-eared Saxufrage)",
    "lifeform": "Perennial",
    "category": "PERENNIALS",
    "comments": "evergreen",
    "ca_native": false,
    "origin": "Central Asia",
    "fire_rating": "Fire-Resistant",
    "recommendation": "",
    "pyrophytic": false
  },
  {
    "scientific_name": "Centaurea cineraria",
    "common_name": "Dusty Miller (Velvet Centaurea)",
    "lifeform": "Perennial",
    "category": "PERENNIALS",
    "comments": "evergreen",
    "ca_native": false,
    "origin": "Italy",
    "fire_rating": "Fire-Resistant",
    "recommendation": "",
    "pyrophytic": false
  },
  {
    "scientific_name": "Clinopodium [Satureja] douglasii",
    "common_name": "Yerba Buena",
    "lifeform": "Perennial, \ngrnd cover",
    "category": "PERENNIALS",
    "comments": "evergreen",
    "ca_native": true,
    "origin": "California Native",
    "fire_rating": "Fire-Resistant",
    "recommendation": "",
    "pyrophytic": false
  },
  {
    "scientific_name": "Cotyledon spp.",
    "common_name": "Cotyledon",
    "lifeform": "Perennial",
    "category": "PERENNIALS",
    "comments": "succulent",
    "ca_native": false,
    "origin": "So. Africa",
    "fire_rating": "Fire-Resistant",
    "recommendation": "",
    "pyrophytic": false
  },
  {
    "scientific_name": "Crassula spp.",
    "common_name": "Crassula",
    "lifeform": "Perennial",
    "category": "PERENNIALS",
    "comments": "succulent",
    "ca_native": false,
    "origin": "So. Africa",
    "fire_rating": "Fire-Resistant",
    "recommendation": "",
    "pyrophytic": false
  },
  {
    "scientific_name": "Dicentra formosa",
    "common_name": "Western (Pacific) Bleeding Heart",
    "lifeform": "Perennial",
    "category": "PERENNIALS",
    "comments": "winter deciduous",
    "ca_native": true,
    "origin": "California Native",
    "fire_rating": "Fire-Resistant",
    "recommendation": "",
    "pyrophytic": false
  },
  {
    "scientific_name": "Dietes bicolor",
    "common_name": "African Iris",
    "lifeform": "Perennial",
    "category": "PERENNIALS",
    "comments": "evergreen",
    "ca_native": false,
    "origin": "So. Africa",
    "fire_rating": "Fire-Resistant",
    "recommendation": "",
    "pyrophytic": false
  },
  {
    "scientific_name": "Dietes vegeta",
    "common_name": "Fortnight Lily",
    "lifeform": "Perennial",
    "category": "PERENNIALS",
    "comments": "evergreen",
    "ca_native": false,
    "origin": "So. Africa",
    "fire_rating": "Fire-Resistant",
    "recommendation": "",
    "pyrophytic": false
  },
  {
    "scientific_name": "Dudleya",
    "common_name": "Dudleya/Cliff Lettuce",
    "lifeform": "Perennial",
    "category": "PERENNIALS",
    "comments": "succulent",
    "ca_native": false,
    "origin": "X  (49 native to CA)",
    "fire_rating": "Fire-Resistant",
    "recommendation": "",
    "pyrophytic": false
  },
  {
    "scientific_name": "Echeveria spp.",
    "common_name": "Hen and Chicks",
    "lifeform": "Perennial",
    "category": "PERENNIALS",
    "comments": "succulent",
    "ca_native": false,
    "origin": "Mexico, Central & \nSo. America",
    "fire_rating": "Fire-Resistant",
    "recommendation": "",
    "pyrophytic": false
  },
  {
    "scientific_name": "Epilobium canum [Zauschneria californica]",
    "common_name": "California Fuchsia",
    "lifeform": "Perennial shrub, grnd cover",
    "category": "PERENNIALS",
    "comments": "winter semi-deciduous",
    "ca_native": true,
    "origin": "California Native",
    "fire_rating": "Fire-Resistant",
    "recommendation": "",
    "pyrophytic": false
  },
  {
    "scientific_name": "Eriogonum spp.",
    "common_name": "Wild Buckwheat",
    "lifeform": "Perennial",
    "category": "PERENNIALS",
    "comments": "evergreen",
    "ca_native": false,
    "origin": "X  (8 native to EB Hills)",
    "fire_rating": "Fire-Resistant",
    "recommendation": "",
    "pyrophytic": false
  },
  {
    "scientific_name": "Eriophyllum confertiforum",
    "common_name": "Golden Yarrow",
    "lifeform": "Perennial, shrub",
    "category": "PERENNIALS",
    "comments": "winter deciduous",
    "ca_native": true,
    "origin": "California Native",
    "fire_rating": "Fire-Resistant",
    "recommendation": "",
    "pyrophytic": false
  },
  {
    "scientific_name": "Eriophyllum stachaedifolium",
    "common_name": "Seaside Woolly Sunflower",
    "lifeform": "Perennial",
    "category": "PERENNIALS",
    "comments": "evergreen",
    "ca_native": true,
    "origin": "California Native",
    "fire_rating": "Fire-Resistant",
    "recommendation": "",
    "pyrophytic": false
  },
  {
    "scientific_name": "Erysimum capitatum",
    "common_name": "Sanddune Wallflower",
    "lifeform": "Perennial",
    "category": "PERENNIALS",
    "comments": "evergreen",
    "ca_native": true,
    "origin": "California Native",
    "fire_rating": "Fire-Resistant",
    "recommendation": "",
    "pyrophytic": false
  },
  {
    "scientific_name": "Erysimum linifolium",
    "common_name": "Wallflower",
    "lifeform": "Perennial",
    "category": "PERENNIALS",
    "comments": "evergreen",
    "ca_native": false,
    "origin": "So. Europe",
    "fire_rating": "Fire-Resistant",
    "recommendation": "",
    "pyrophytic": false
  },
  {
    "scientific_name": "Eschscholzia spp.",
    "common_name": "California Poppy",
    "lifeform": "Perennial",
    "category": "PERENNIALS",
    "comments": "summer deciduous",
    "ca_native": false,
    "origin": "X  (2 native to EB Hills)",
    "fire_rating": "Fire-Resistant",
    "recommendation": "",
    "pyrophytic": false
  },
  {
    "scientific_name": "Grindelia stricta",
    "common_name": "Oregon Gumweed",
    "lifeform": "Perennial",
    "category": "PERENNIALS",
    "comments": "summer semi-deciduous",
    "ca_native": true,
    "origin": "California Native",
    "fire_rating": "Fire-Resistant",
    "recommendation": "",
    "pyrophytic": false
  },
  {
    "scientific_name": "Grindelia camporum",
    "common_name": "Great Valley Gumweed (Wild Gum)",
    "lifeform": "Perennial",
    "category": "PERENNIALS",
    "comments": "summer semi-deciduous",
    "ca_native": true,
    "origin": "California Native",
    "fire_rating": "Fire-Resistant",
    "recommendation": "",
    "pyrophytic": false
  },
  {
    "scientific_name": "Hemerocallis hybrids",
    "common_name": "Daylily",
    "lifeform": "Perennial",
    "category": "PERENNIALS",
    "comments": "evergreen",
    "ca_native": false,
    "origin": "E. Asia",
    "fire_rating": "Fire-Resistant",
    "recommendation": "",
    "pyrophytic": false
  },
  {
    "scientific_name": "Hesperaloe parviflora",
    "common_name": "Red Yucca",
    "lifeform": "Perennial",
    "category": "PERENNIALS",
    "comments": "succulent",
    "ca_native": false,
    "origin": "Texas, Mexico",
    "fire_rating": "Fire-Resistant",
    "recommendation": "",
    "pyrophytic": false
  },
  {
    "scientific_name": "Heuchera maxima",
    "common_name": "Island Alum Root",
    "lifeform": "Perennial",
    "category": "PERENNIALS",
    "comments": "evergreen",
    "ca_native": true,
    "origin": "California Native",
    "fire_rating": "Fire-Resistant",
    "recommendation": "",
    "pyrophytic": false
  },
  {
    "scientific_name": "Heuchera micrantha",
    "common_name": "Coral Bells",
    "lifeform": "Perennial, \ngrnd cvr",
    "category": "PERENNIALS",
    "comments": "evergreen",
    "ca_native": true,
    "origin": "California Native",
    "fire_rating": "Fire-Resistant",
    "recommendation": "",
    "pyrophytic": false
  },
  {
    "scientific_name": "Iris douglasiana",
    "common_name": "Douglas Iris",
    "lifeform": "Perennial",
    "category": "PERENNIALS",
    "comments": "evergreen",
    "ca_native": true,
    "origin": "California Native",
    "fire_rating": "Fire-Resistant",
    "recommendation": "",
    "pyrophytic": false
  },
  {
    "scientific_name": "Iris macrosiphon",
    "common_name": "Ground Iris (Long tubed Iris)",
    "lifeform": "Perennial",
    "category": "PERENNIALS",
    "comments": "winter deciduous",
    "ca_native": true,
    "origin": "California Native",
    "fire_rating": "Fire-Resistant",
    "recommendation": "",
    "pyrophytic": false
  },
  {
    "scientific_name": "Kniphofia uvaria",
    "common_name": "Red Hot Poker (Torch Lily)",
    "lifeform": "Perennial",
    "category": "PERENNIALS",
    "comments": "evergreen",
    "ca_native": false,
    "origin": "So. Africa",
    "fire_rating": "Fire-Resistant",
    "recommendation": "",
    "pyrophytic": false
  },
  {
    "scientific_name": "Lupinus spp.",
    "common_name": "Lupine",
    "lifeform": "Perennial",
    "category": "PERENNIALS",
    "comments": "evergreen",
    "ca_native": false,
    "origin": "X  (18 native to EB hills)",
    "fire_rating": "Fire-Resistant",
    "recommendation": "",
    "pyrophytic": false
  },
  {
    "scientific_name": "Mimulus aurantiacus",
    "common_name": "Monkey Flower",
    "lifeform": "Perennial, Shrub",
    "category": "PERENNIALS",
    "comments": "evergreen",
    "ca_native": true,
    "origin": "California Native",
    "fire_rating": "Fire-Resistant",
    "recommendation": "",
    "pyrophytic": false
  },
  {
    "scientific_name": "Mimulus guttatus",
    "common_name": "Seep Monkey Flower",
    "lifeform": "Perennial, Shrub",
    "category": "PERENNIALS",
    "comments": "evergreen",
    "ca_native": true,
    "origin": "California Native",
    "fire_rating": "Fire-Resistant",
    "recommendation": "",
    "pyrophytic": false
  },
  {
    "scientific_name": "Monardella villosa",
    "common_name": "Coyote Mint",
    "lifeform": "Perennial",
    "category": "PERENNIALS",
    "comments": "summer semi-deciduous",
    "ca_native": true,
    "origin": "California Native",
    "fire_rating": "Fire-Resistant",
    "recommendation": "",
    "pyrophytic": false
  },
  {
    "scientific_name": "Oenothera berlandieri (speciosa)",
    "common_name": "Mexican Evening Primrose",
    "lifeform": "Perennial",
    "category": "PERENNIALS",
    "comments": "summer semi-deciduous",
    "ca_native": false,
    "origin": "Texas, Mexico",
    "fire_rating": "Fire-Resistant",
    "recommendation": "",
    "pyrophytic": false
  },
  {
    "scientific_name": "Penstemon spp.",
    "common_name": "Beard Tongue",
    "lifeform": "Perennial",
    "category": "PERENNIALS",
    "comments": "evergreen",
    "ca_native": false,
    "origin": "X  (2 native to EB Hills)",
    "fire_rating": "Fire-Resistant",
    "recommendation": "",
    "pyrophytic": false
  },
  {
    "scientific_name": "Polystichum munitum",
    "common_name": "Sword Fern",
    "lifeform": "Perennial",
    "category": "PERENNIALS",
    "comments": "summer semi-deciduous",
    "ca_native": true,
    "origin": "California Native",
    "fire_rating": "Fire-Resistant",
    "recommendation": "",
    "pyrophytic": false
  },
  {
    "scientific_name": "Portulacaria afra \"Variegata\"",
    "common_name": "Elephant's Foot (Miniature Jade)",
    "lifeform": "Perennial",
    "category": "PERENNIALS",
    "comments": "succulent",
    "ca_native": false,
    "origin": "So. Africa",
    "fire_rating": "Fire-Resistant",
    "recommendation": "",
    "pyrophytic": false
  },
  {
    "scientific_name": "Ranunculus californica",
    "common_name": "Buttercup",
    "lifeform": "Perennial",
    "category": "PERENNIALS",
    "comments": "summer deciduous",
    "ca_native": true,
    "origin": "California Native",
    "fire_rating": "Fire-Resistant",
    "recommendation": "",
    "pyrophytic": false
  },
  {
    "scientific_name": "Romneya coulteri",
    "common_name": "Matilija Poppy",
    "lifeform": "Perennial",
    "category": "PERENNIALS",
    "comments": "summer deciduous",
    "ca_native": true,
    "origin": "California Native",
    "fire_rating": "Fire-Resistant",
    "recommendation": "",
    "pyrophytic": false
  },
  {
    "scientific_name": "Sidalcea malviflora",
    "common_name": "Checkerbloom",
    "lifeform": "Perennial",
    "category": "PERENNIALS",
    "comments": "summer semi-deciduous",
    "ca_native": true,
    "origin": "California Native",
    "fire_rating": "Fire-Resistant",
    "recommendation": "",
    "pyrophytic": false
  },
  {
    "scientific_name": "Sisyrinchium bellum,\nS. californicum",
    "common_name": "Blue-eyed Grass/Yellow-eyed Grass",
    "lifeform": "Perennial",
    "category": "PERENNIALS",
    "comments": "summer semi-deciduous",
    "ca_native": false,
    "origin": "X  (1 native to EB Hills)",
    "fire_rating": "Fire-Resistant",
    "recommendation": "",
    "pyrophytic": false
  },
  {
    "scientific_name": "Stachys byzantina",
    "common_name": "Lamb's Ears",
    "lifeform": "Perennial",
    "category": "PERENNIALS",
    "comments": "winter deciduous",
    "ca_native": false,
    "origin": "Turkey, Armenia",
    "fire_rating": "Fire-Resistant",
    "recommendation": "",
    "pyrophytic": false
  },
  {
    "scientific_name": "Strelitzia reginae",
    "common_name": "Bird of Paradise",
    "lifeform": "Perennial, Shrub",
    "category": "PERENNIALS",
    "comments": "evergreen",
    "ca_native": false,
    "origin": "So. Africa",
    "fire_rating": "Fire-Resistant",
    "recommendation": "",
    "pyrophytic": false
  },
  {
    "scientific_name": "Symphotrichum chilensis",
    "common_name": "Wild Aster (California Aster)",
    "lifeform": "Perennial",
    "category": "PERENNIALS",
    "comments": "winter deciduous",
    "ca_native": true,
    "origin": "California Native",
    "fire_rating": "Fire-Resistant",
    "recommendation": "",
    "pyrophytic": false
  },
  {
    "scientific_name": "Toxicoscordion [Zigadenus] fremontii",
    "common_name": "Star Lily",
    "lifeform": "Perennial",
    "category": "PERENNIALS",
    "comments": "evergreen",
    "ca_native": true,
    "origin": "California Native",
    "fire_rating": "Fire-Resistant",
    "recommendation": "",
    "pyrophytic": false
  },
  {
    "scientific_name": "Triteleia [Brodiaea] laxa",
    "common_name": "Grass Nut (Ithuriel's Spear)",
    "lifeform": "Perennial",
    "category": "PERENNIALS",
    "comments": "summer deciduous",
    "ca_native": true,
    "origin": "California Native",
    "fire_rating": "Fire-Resistant",
    "recommendation": "",
    "pyrophytic": false
  },
  {
    "scientific_name": "Tulbaghia violocea",
    "common_name": "Society Garlic (Pink Agapanthus)",
    "lifeform": "Perennial",
    "category": "PERENNIALS",
    "comments": "evergreen",
    "ca_native": false,
    "origin": "So. Africa",
    "fire_rating": "Fire-Resistant",
    "recommendation": "",
    "pyrophytic": false
  },
  {
    "scientific_name": "Arctostaphylos ssp. (some)",
    "common_name": "Manzanita",
    "lifeform": "shrub",
    "category": "SHRUBS",
    "comments": "evergreen",
    "ca_native": false,
    "origin": "X  (8 native to EB Hills)",
    "fire_rating": "Fire-Resistant",
    "recommendation": "",
    "pyrophytic": false
  },
  {
    "scientific_name": "Artemisia pycnocephala",
    "common_name": "Sandhill sage (Coastal Sagewort)",
    "lifeform": "shrub",
    "category": "SHRUBS",
    "comments": "evergreen",
    "ca_native": true,
    "origin": "California Native",
    "fire_rating": "Fire-Resistant",
    "recommendation": "",
    "pyrophytic": false
  },
  {
    "scientific_name": "Atriplex lentiformis breweri",
    "common_name": "Saltbush (Quail bush)",
    "lifeform": "shrub",
    "category": "SHRUBS",
    "comments": "evergreen,  can be invasive",
    "ca_native": true,
    "origin": "California Native",
    "fire_rating": "Fire-Resistant",
    "recommendation": "",
    "pyrophytic": false
  },
  {
    "scientific_name": "Berberis [Mahonia] aquifolium var. repens",
    "common_name": "Dwarf Mahonia (Oregon Grape)",
    "lifeform": "Shrub",
    "category": "SHRUBS",
    "comments": "evergreen",
    "ca_native": true,
    "origin": "California Native",
    "fire_rating": "Fire-Resistant",
    "recommendation": "",
    "pyrophytic": false
  },
  {
    "scientific_name": "Brugmansia spp.",
    "common_name": "Angel's Trumpet",
    "lifeform": "Shrub",
    "category": "SHRUBS",
    "comments": "poisonous",
    "ca_native": false,
    "origin": "So. America",
    "fire_rating": "Fire-Resistant",
    "recommendation": "",
    "pyrophytic": false
  },
  {
    "scientific_name": "Carpenteria californica",
    "common_name": "Bush Anemone",
    "lifeform": "Shrub",
    "category": "SHRUBS",
    "comments": "evergreen",
    "ca_native": true,
    "origin": "California Native",
    "fire_rating": "Fire-Resistant",
    "recommendation": "",
    "pyrophytic": false
  },
  {
    "scientific_name": "Ceanothus thrysiflorus",
    "common_name": "California Lilac (Blueblossom)",
    "lifeform": "shrub",
    "category": "SHRUBS",
    "comments": "evergreen",
    "ca_native": true,
    "origin": "California Native",
    "fire_rating": "Fire-Resistant",
    "recommendation": "",
    "pyrophytic": false
  },
  {
    "scientific_name": "Coleonema pulchellum  (Diosma)",
    "common_name": "Breath of Heaven",
    "lifeform": "Shrub",
    "category": "SHRUBS",
    "comments": "",
    "ca_native": false,
    "origin": "So. Africa",
    "fire_rating": "Fire-Resistant",
    "recommendation": "",
    "pyrophytic": false
  },
  {
    "scientific_name": "Convolvulus cneorum",
    "common_name": "Bush Morning Glory (Silverbush)",
    "lifeform": "Shrub",
    "category": "SHRUBS",
    "comments": "evergreen",
    "ca_native": false,
    "origin": "Europe",
    "fire_rating": "Fire-Resistant",
    "recommendation": "",
    "pyrophytic": false
  },
  {
    "scientific_name": "Coreopsis spp.",
    "common_name": "Stillman's Coreopsis/ \nGiant Coreopsis/Sea Dahlia",
    "lifeform": "Shrub",
    "category": "SHRUBS",
    "comments": "evergreen",
    "ca_native": false,
    "origin": "X  (5 native to CA)",
    "fire_rating": "Fire-Resistant",
    "recommendation": "",
    "pyrophytic": false
  },
  {
    "scientific_name": "Escallonia spp.",
    "common_name": "Escallonia",
    "lifeform": "Shrub",
    "category": "SHRUBS",
    "comments": "",
    "ca_native": false,
    "origin": "So. America",
    "fire_rating": "Fire-Resistant",
    "recommendation": "",
    "pyrophytic": false
  },
  {
    "scientific_name": "Feijoa [Acca] sellowiana",
    "common_name": "Pineapple Guava",
    "lifeform": "Shrub, tree",
    "category": "SHRUBS",
    "comments": "evergreen, edible fruit",
    "ca_native": false,
    "origin": "So. America",
    "fire_rating": "Fire-Resistant",
    "recommendation": "",
    "pyrophytic": false
  },
  {
    "scientific_name": "Fremotodendron spp.",
    "common_name": "Fremontia (Flannel Bush)",
    "lifeform": "shrub",
    "category": "SHRUBS",
    "comments": "evergreen",
    "ca_native": false,
    "origin": "X  (3 native to CA)",
    "fire_rating": "Fire-Resistant",
    "recommendation": "",
    "pyrophytic": false
  },
  {
    "scientific_name": "Galvezia [Gambelia] speciosa",
    "common_name": "Showy Island snapdragon (Hummingbird Flower)",
    "lifeform": "shrub",
    "category": "SHRUBS",
    "comments": "evergreen",
    "ca_native": true,
    "origin": "California Native",
    "fire_rating": "Fire-Resistant",
    "recommendation": "",
    "pyrophytic": false
  },
  {
    "scientific_name": "Heteromeles arbutifolia",
    "common_name": "Toyon",
    "lifeform": "shrub",
    "category": "SHRUBS",
    "comments": "evergreen",
    "ca_native": true,
    "origin": "California Native",
    "fire_rating": "Fire-Resistant",
    "recommendation": "",
    "pyrophytic": false
  },
  {
    "scientific_name": "Lantana montevidensis",
    "common_name": "Lantana (Weeping Lantana)",
    "lifeform": "Shrub",
    "category": "SHRUBS",
    "comments": "evergreen",
    "ca_native": false,
    "origin": "So. America",
    "fire_rating": "Fire-Resistant",
    "recommendation": "",
    "pyrophytic": false
  },
  {
    "scientific_name": "Lavandula spp.",
    "common_name": "Lavender",
    "lifeform": "Shrub",
    "category": "SHRUBS",
    "comments": "",
    "ca_native": false,
    "origin": "Europe, Africa, Mediterranean, Asia",
    "fire_rating": "Fire-Resistant",
    "recommendation": "",
    "pyrophytic": false
  },
  {
    "scientific_name": "Lavatera assurgentiflora",
    "common_name": "Malva Rosa\n(Island Mallow, Tree Mallow)",
    "lifeform": "Shrub",
    "category": "SHRUBS",
    "comments": "evergreen",
    "ca_native": true,
    "origin": "California Native",
    "fire_rating": "Fire-Resistant",
    "recommendation": "",
    "pyrophytic": false
  },
  {
    "scientific_name": "Mimulus [longiflorus] aurantiacus",
    "common_name": "Monkey Flower",
    "lifeform": "shrub",
    "category": "SHRUBS",
    "comments": "perennial",
    "ca_native": true,
    "origin": "California Native",
    "fire_rating": "Fire-Resistant",
    "recommendation": "",
    "pyrophytic": false
  },
  {
    "scientific_name": "Morella [Myrica] californica",
    "common_name": "California Wax Myrtle",
    "lifeform": "shrub, grnd covr",
    "category": "SHRUBS",
    "comments": "evergreen",
    "ca_native": true,
    "origin": "California Native",
    "fire_rating": "Fire-Resistant",
    "recommendation": "",
    "pyrophytic": false
  },
  {
    "scientific_name": "Nolina spp.",
    "common_name": "Nolina (Beargrass)",
    "lifeform": "Shrub",
    "category": "SHRUBS",
    "comments": "evergreen",
    "ca_native": false,
    "origin": "X  (4 native to CA)",
    "fire_rating": "Fire-Resistant",
    "recommendation": "",
    "pyrophytic": false
  },
  {
    "scientific_name": "Prunus ilicifolia",
    "common_name": "Holly-leafed cherry",
    "lifeform": "shrub",
    "category": "SHRUBS",
    "comments": "evergreen, edible fruit",
    "ca_native": true,
    "origin": "California Native",
    "fire_rating": "Fire-Resistant",
    "recommendation": "",
    "pyrophytic": false
  },
  {
    "scientific_name": "Prunus ilicifolia subsp lyonii",
    "common_name": "Catalina Cherry",
    "lifeform": "Shrub",
    "category": "SHRUBS",
    "comments": "evergreen",
    "ca_native": true,
    "origin": "California Native",
    "fire_rating": "Fire-Resistant",
    "recommendation": "",
    "pyrophytic": false
  },
  {
    "scientific_name": "Punica granatum",
    "common_name": "Pomegranate",
    "lifeform": "Shrub",
    "category": "SHRUBS",
    "comments": "evergreen",
    "ca_native": false,
    "origin": "Middle East",
    "fire_rating": "Fire-Resistant",
    "recommendation": "",
    "pyrophytic": false
  },
  {
    "scientific_name": "Frangula [Rhamnus] californica",
    "common_name": "Coffeeberry (California Buckthorn)",
    "lifeform": "shrub",
    "category": "SHRUBS",
    "comments": "evergreen",
    "ca_native": true,
    "origin": "California Native",
    "fire_rating": "Fire-Resistant",
    "recommendation": "",
    "pyrophytic": false
  },
  {
    "scientific_name": "Rhamnus crocea",
    "common_name": "Redberry (Red-berried Buckthorn)",
    "lifeform": "shrub",
    "category": "SHRUBS",
    "comments": "evergreen",
    "ca_native": true,
    "origin": "California Native",
    "fire_rating": "Fire-Resistant",
    "recommendation": "",
    "pyrophytic": false
  },
  {
    "scientific_name": "Rhaphiolepis spp.",
    "common_name": "India Hawthorn",
    "lifeform": "Shrub",
    "category": "SHRUBS",
    "comments": "evergreen",
    "ca_native": false,
    "origin": "Asia",
    "fire_rating": "Fire-Resistant",
    "recommendation": "",
    "pyrophytic": false
  },
  {
    "scientific_name": "Rhododendron [Azalea] spp.",
    "common_name": "Rhododendrons and Azaleas",
    "lifeform": "Shrub",
    "category": "SHRUBS",
    "comments": "some",
    "ca_native": false,
    "origin": "X  (6 native to CA)",
    "fire_rating": "Fire-Resistant",
    "recommendation": "",
    "pyrophytic": false
  },
  {
    "scientific_name": "Rhododrendron occidentale",
    "common_name": "Western (Sonoma) Azalea",
    "lifeform": "shrub",
    "category": "SHRUBS",
    "comments": "deciduous",
    "ca_native": true,
    "origin": "California Native",
    "fire_rating": "Fire-Resistant",
    "recommendation": "",
    "pyrophytic": false
  },
  {
    "scientific_name": "Rhus integrifolia",
    "common_name": "Lemonade Berry (Lemonade Sumac)",
    "lifeform": "shrub",
    "category": "SHRUBS",
    "comments": "evergreen",
    "ca_native": true,
    "origin": "California Native",
    "fire_rating": "Fire-Resistant",
    "recommendation": "",
    "pyrophytic": false
  },
  {
    "scientific_name": "Ribes sanguineum",
    "common_name": "Pink Flowering Currant",
    "lifeform": "shrub",
    "category": "SHRUBS",
    "comments": "evergreen",
    "ca_native": true,
    "origin": "California Native",
    "fire_rating": "Fire-Resistant",
    "recommendation": "",
    "pyrophytic": false
  },
  {
    "scientific_name": "Ribes viburnifolium",
    "common_name": "Evergreen Currant\n(Catalina Perfume)",
    "lifeform": "shrub",
    "category": "SHRUBS",
    "comments": "evergreen",
    "ca_native": true,
    "origin": "California Native",
    "fire_rating": "Fire-Resistant",
    "recommendation": "",
    "pyrophytic": false
  },
  {
    "scientific_name": "Salvia sonomensis",
    "common_name": "Sonoma Sage",
    "lifeform": "shrub",
    "category": "SHRUBS",
    "comments": "perennial",
    "ca_native": true,
    "origin": "California Native",
    "fire_rating": "Fire-Resistant",
    "recommendation": "",
    "pyrophytic": false
  },
  {
    "scientific_name": "Santolina chamaecyparissus",
    "common_name": "Santolina Lavender\n(Gray Lavender)",
    "lifeform": "shrub, grnd covr",
    "category": "SHRUBS",
    "comments": "evergreen",
    "ca_native": false,
    "origin": "Mediterranean",
    "fire_rating": "Fire-Resistant",
    "recommendation": "",
    "pyrophytic": false
  },
  {
    "scientific_name": "Simmondsia chinensis",
    "common_name": "Jojoba",
    "lifeform": "Shrub",
    "category": "SHRUBS",
    "comments": "evergreen",
    "ca_native": true,
    "origin": "California Native",
    "fire_rating": "Fire-Resistant",
    "recommendation": "",
    "pyrophytic": false
  },
  {
    "scientific_name": "Solanum xanti",
    "common_name": "Purple Nightshade",
    "lifeform": "Shrub",
    "category": "SHRUBS",
    "comments": "poisonous, summer  semi-deciduous",
    "ca_native": true,
    "origin": "California Native",
    "fire_rating": "Fire-Resistant",
    "recommendation": "",
    "pyrophytic": false
  },
  {
    "scientific_name": "Trachelospermum jasminoides",
    "common_name": "Star Jasmine",
    "lifeform": "Shrub",
    "category": "SHRUBS",
    "comments": "evergreen",
    "ca_native": false,
    "origin": "S.E. Asia",
    "fire_rating": "Fire-Resistant",
    "recommendation": "",
    "pyrophytic": false
  },
  {
    "scientific_name": "Trichostema lanatum",
    "common_name": "Wooly blue curls (Romero)",
    "lifeform": "shrub",
    "category": "SHRUBS",
    "comments": "perennial",
    "ca_native": true,
    "origin": "California Native",
    "fire_rating": "Fire-Resistant",
    "recommendation": "",
    "pyrophytic": false
  },
  {
    "scientific_name": "Vaccinium corymbosum",
    "common_name": "Blueberry",
    "lifeform": "Shrub",
    "category": "SHRUBS",
    "comments": "deciduous",
    "ca_native": false,
    "origin": "East U.S. & Canada",
    "fire_rating": "Fire-Resistant",
    "recommendation": "",
    "pyrophytic": false
  },
  {
    "scientific_name": "Yucca spp.",
    "common_name": "Yucca",
    "lifeform": "Shrub",
    "category": "SHRUBS",
    "comments": "evergreen",
    "ca_native": false,
    "origin": "Mexico, So. America",
    "fire_rating": "Fire-Resistant",
    "recommendation": "",
    "pyrophytic": false
  },
  {
    "scientific_name": "Acer spp.",
    "common_name": "Maple",
    "lifeform": "Tree",
    "category": "TREES",
    "comments": "winter deciduous",
    "ca_native": false,
    "origin": "X  (2 native to EB Hills)",
    "fire_rating": "Fire-Resistant",
    "recommendation": "",
    "pyrophytic": false
  },
  {
    "scientific_name": "Aesculus californica",
    "common_name": "California Buckeye",
    "lifeform": "tree",
    "category": "TREES",
    "comments": "winter deciduous",
    "ca_native": true,
    "origin": "California Native",
    "fire_rating": "Fire-Resistant",
    "recommendation": "",
    "pyrophytic": false
  },
  {
    "scientific_name": "Alnus rhombifolia",
    "common_name": "White Alder",
    "lifeform": "tree",
    "category": "TREES",
    "comments": "winter deciduous",
    "ca_native": true,
    "origin": "California Native",
    "fire_rating": "Fire-Resistant",
    "recommendation": "",
    "pyrophytic": false
  },
  {
    "scientific_name": "Arbutus menziesii",
    "common_name": "Madrone",
    "lifeform": "tree",
    "category": "TREES",
    "comments": "evergreen",
    "ca_native": true,
    "origin": "California Native",
    "fire_rating": "Fire-Resistant",
    "recommendation": "",
    "pyrophytic": false
  },
  {
    "scientific_name": "Arbutus unedo",
    "common_name": "Strawberry Tree",
    "lifeform": "Tree",
    "category": "TREES",
    "comments": "evergreen, fruiting",
    "ca_native": false,
    "origin": "Mediterranean",
    "fire_rating": "Fire-Resistant",
    "recommendation": "",
    "pyrophytic": false
  },
  {
    "scientific_name": "Ceratonia siliqua",
    "common_name": "Carob",
    "lifeform": "Tree",
    "category": "TREES",
    "comments": "",
    "ca_native": false,
    "origin": "Mediterranean, Asia",
    "fire_rating": "Fire-Resistant",
    "recommendation": "",
    "pyrophytic": false
  },
  {
    "scientific_name": "Cercis occidentalis",
    "common_name": "Western Redbud",
    "lifeform": "Tree",
    "category": "TREES",
    "comments": "winter deciduous",
    "ca_native": true,
    "origin": "California Native",
    "fire_rating": "Fire-Resistant",
    "recommendation": "",
    "pyrophytic": false
  },
  {
    "scientific_name": "Cercocarpus betuloides",
    "common_name": "Mountain Ironwood \n(Mountain Mahogany)",
    "lifeform": "Tree",
    "category": "TREES",
    "comments": "evergreen",
    "ca_native": true,
    "origin": "California Native",
    "fire_rating": "Fire-Resistant",
    "recommendation": "",
    "pyrophytic": false
  },
  {
    "scientific_name": "Citrus spp.",
    "common_name": "Citrus",
    "lifeform": "Tree",
    "category": "TREES",
    "comments": "evergreen",
    "ca_native": false,
    "origin": "S.E. Asia",
    "fire_rating": "Fire-Resistant",
    "recommendation": "",
    "pyrophytic": false
  },
  {
    "scientific_name": "Fagus spp.",
    "common_name": "Beech",
    "lifeform": "Tree",
    "category": "TREES",
    "comments": "",
    "ca_native": false,
    "origin": "Eurasia, No. America",
    "fire_rating": "Fire-Resistant",
    "recommendation": "",
    "pyrophytic": false
  },
  {
    "scientific_name": "Fraxinus spp.",
    "common_name": "Ash",
    "lifeform": "Tree",
    "category": "TREES",
    "comments": "winter deciduous",
    "ca_native": false,
    "origin": "X  (5 native to CA)",
    "fire_rating": "Fire-Resistant",
    "recommendation": "",
    "pyrophytic": false
  },
  {
    "scientific_name": "Fraxinus dipetala",
    "common_name": "California Ash",
    "lifeform": "Tree",
    "category": "TREES",
    "comments": "winter deciduous",
    "ca_native": true,
    "origin": "California Native",
    "fire_rating": "Fire-Resistant",
    "recommendation": "",
    "pyrophytic": false
  },
  {
    "scientific_name": "Fraxinus latifolia",
    "common_name": "Oregon Ash",
    "lifeform": "Tree",
    "category": "TREES",
    "comments": "winter deciduous",
    "ca_native": true,
    "origin": "California Native",
    "fire_rating": "Fire-Resistant",
    "recommendation": "",
    "pyrophytic": false
  },
  {
    "scientific_name": "Fraxinus ornus",
    "common_name": "Flowering Ash",
    "lifeform": "Tree",
    "category": "TREES",
    "comments": "winter deciduous",
    "ca_native": false,
    "origin": "Europe",
    "fire_rating": "Fire-Resistant",
    "recommendation": "",
    "pyrophytic": false
  },
  {
    "scientific_name": "Macadamia hybrids",
    "common_name": "Macadamia Nut",
    "lifeform": "Tree",
    "category": "TREES",
    "comments": "evergreen",
    "ca_native": false,
    "origin": "Australia",
    "fire_rating": "Fire-Resistant",
    "recommendation": "",
    "pyrophytic": false
  },
  {
    "scientific_name": "Metrosideros excelsa",
    "common_name": "New Zealand Christmas Tree",
    "lifeform": "Tree",
    "category": "TREES",
    "comments": "evergreen",
    "ca_native": false,
    "origin": "New Zealand",
    "fire_rating": "Fire-Resistant",
    "recommendation": "",
    "pyrophytic": false
  },
  {
    "scientific_name": "Pistacia chinensis",
    "common_name": "Chinese Pistache",
    "lifeform": "Tree",
    "category": "TREES",
    "comments": "winter deciduous",
    "ca_native": false,
    "origin": "China",
    "fire_rating": "Fire-Resistant",
    "recommendation": "",
    "pyrophytic": false
  },
  {
    "scientific_name": "Populus spp.",
    "common_name": "Aspen/Cottonwood/Poplar/\nQuaking Aspen",
    "lifeform": "tree",
    "category": "TREES",
    "comments": "deciduous",
    "ca_native": false,
    "origin": "X  (5 native to CA)",
    "fire_rating": "Fire-Resistant",
    "recommendation": "",
    "pyrophytic": false
  },
  {
    "scientific_name": "Populus fremontii",
    "common_name": "Fremont Cottonwood",
    "lifeform": "tree",
    "category": "TREES",
    "comments": "deciduous",
    "ca_native": false,
    "origin": "X  (2 native to EB Hills)",
    "fire_rating": "Fire-Resistant",
    "recommendation": "",
    "pyrophytic": false
  },
  {
    "scientific_name": "Quercus spp.",
    "common_name": "Oak",
    "lifeform": "",
    "category": "TREES",
    "comments": "",
    "ca_native": false,
    "origin": "X  (36 native to CA)",
    "fire_rating": "Fire-Resistant",
    "recommendation": "",
    "pyrophytic": false
  },
  {
    "scientific_name": "Quercus agrifola",
    "common_name": "Coast Live Oak",
    "lifeform": "tree",
    "category": "TREES",
    "comments": "evergreen",
    "ca_native": true,
    "origin": "California Native",
    "fire_rating": "Fire-Resistant",
    "recommendation": "",
    "pyrophytic": false
  },
  {
    "scientific_name": "Quercus engelmannii",
    "common_name": "Engelmann Oak",
    "lifeform": "Tree",
    "category": "TREES",
    "comments": "deciduous",
    "ca_native": true,
    "origin": "California Native",
    "fire_rating": "Fire-Resistant",
    "recommendation": "",
    "pyrophytic": false
  },
  {
    "scientific_name": "Quercus dumosa",
    "common_name": "Coastal Scrub Oak \n(Nuttal's Scrub Oak)",
    "lifeform": "Tree",
    "category": "TREES",
    "comments": "evergreen",
    "ca_native": true,
    "origin": "California Native",
    "fire_rating": "Fire-Resistant",
    "recommendation": "",
    "pyrophytic": false
  },
  {
    "scientific_name": "Quercus frainetto",
    "common_name": "Hungarian Oak",
    "lifeform": "Tree",
    "category": "TREES",
    "comments": "deciduous",
    "ca_native": false,
    "origin": "Europe",
    "fire_rating": "Fire-Resistant",
    "recommendation": "",
    "pyrophytic": false
  },
  {
    "scientific_name": "Quercus gambelli",
    "common_name": "Gambel Oak",
    "lifeform": "Tree",
    "category": "TREES",
    "comments": "deciduous",
    "ca_native": false,
    "origin": "SW U.S.",
    "fire_rating": "Fire-Resistant",
    "recommendation": "",
    "pyrophytic": false
  },
  {
    "scientific_name": "Quercus lobata",
    "common_name": "Valley Oak",
    "lifeform": "Tree",
    "category": "TREES",
    "comments": "deciduous",
    "ca_native": true,
    "origin": "California Native",
    "fire_rating": "Fire-Resistant",
    "recommendation": "",
    "pyrophytic": false
  },
  {
    "scientific_name": "Quercus shrevei",
    "common_name": "Shreve Oak",
    "lifeform": "Tree",
    "category": "TREES",
    "comments": "evergreen",
    "ca_native": true,
    "origin": "California Native",
    "fire_rating": "Fire-Resistant",
    "recommendation": "",
    "pyrophytic": false
  },
  {
    "scientific_name": "Quercus suber",
    "common_name": "Cork Oak",
    "lifeform": "Tree",
    "category": "TREES",
    "comments": "evergreen",
    "ca_native": false,
    "origin": "Mediterranean, No. Africa",
    "fire_rating": "Fire-Resistant",
    "recommendation": "",
    "pyrophytic": false
  },
  {
    "scientific_name": "Rhus lancea",
    "common_name": "African Sumac",
    "lifeform": "Tree",
    "category": "TREES",
    "comments": "evergreen",
    "ca_native": false,
    "origin": "So. Africa",
    "fire_rating": "Fire-Resistant",
    "recommendation": "",
    "pyrophytic": false
  },
  {
    "scientific_name": "Lonicera hispidula",
    "common_name": "Pink Honeysuckle",
    "lifeform": "Vine",
    "category": "TREES",
    "comments": "winter deciduous",
    "ca_native": true,
    "origin": "California Native",
    "fire_rating": "Fire-Resistant",
    "recommendation": "",
    "pyrophytic": false
  },
  {
    "scientific_name": "Rosa banksiae",
    "common_name": "Lady Banks' Rose",
    "lifeform": "Vine",
    "category": "TREES",
    "comments": "evergreen",
    "ca_native": false,
    "origin": "China",
    "fire_rating": "Fire-Resistant",
    "recommendation": "",
    "pyrophytic": false
  },
  {
    "scientific_name": "Solanum jasminoides [laxum]",
    "common_name": "Potato Vine",
    "lifeform": "Vine",
    "category": "TREES",
    "comments": "evergreen",
    "ca_native": false,
    "origin": "So. America",
    "fire_rating": "Fire-Resistant",
    "recommendation": "",
    "pyrophytic": false
  },
  {
    "scientific_name": "Symphoricarpos mollis",
    "common_name": "Creeping Snowberry",
    "lifeform": "Vine, grnd cvr",
    "category": "TREES",
    "comments": "toxic to humans, evergreen",
    "ca_native": true,
    "origin": "California Native",
    "fire_rating": "Fire-Resistant",
    "recommendation": "",
    "pyrophytic": false
  },
  {
    "scientific_name": "Tecomaria capensis",
    "common_name": "Cape Honeysuckle",
    "lifeform": "Vine",
    "category": "TREES",
    "comments": "evergreen",
    "ca_native": false,
    "origin": "So. Africa",
    "fire_rating": "Fire-Resistant",
    "recommendation": "",
    "pyrophytic": false
  },
  {
    "scientific_name": "Adenostoma fasciculatum",
    "common_name": "Chamis, Greasewood",
    "lifeform": "Shrub",
    "category": "GRASSES, GROUND COVERS & SHRUBS",
    "comments": "",
    "ca_native": true,
    "origin": "California Native",
    "fire_rating": "Fire-Prone",
    "recommendation": "Remove",
    "pyrophytic": true
  },
  {
    "scientific_name": "Adenostoma sparsifolium",
    "common_name": "Red Shanks",
    "lifeform": "Shrub",
    "category": "GRASSES, GROUND COVERS & SHRUBS",
    "comments": "",
    "ca_native": true,
    "origin": "California Native",
    "fire_rating": "Fire-Prone",
    "recommendation": "Avoid",
    "pyrophytic": false
  },
  {
    "scientific_name": "Arctostaphylos spp. (some)",
    "common_name": "Manzanita",
    "lifeform": "Shrub",
    "category": "GRASSES, GROUND COVERS & SHRUBS",
    "comments": "",
    "ca_native": true,
    "origin": "California Native",
    "fire_rating": "Fire-Prone",
    "recommendation": "Avoid",
    "pyrophytic": false
  },
  {
    "scientific_name": "Artemesia californica",
    "common_name": "California sagebrush",
    "lifeform": "Shrub",
    "category": "GRASSES, GROUND COVERS & SHRUBS",
    "comments": "",
    "ca_native": true,
    "origin": "California Native",
    "fire_rating": "Fire-Prone",
    "recommendation": "Remove",
    "pyrophytic": true
  },
  {
    "scientific_name": "Baccharis spp. (when overgrown)",
    "common_name": "Coyote Brush",
    "lifeform": "Shrub, grnd cvr",
    "category": "GRASSES, GROUND COVERS & SHRUBS",
    "comments": "",
    "ca_native": true,
    "origin": "California Native",
    "fire_rating": "Fire-Prone",
    "recommendation": "Remove",
    "pyrophytic": true
  },
  {
    "scientific_name": "Bambusa spp.",
    "common_name": "Bamboo",
    "lifeform": "Perennial",
    "category": "GRASSES, GROUND COVERS & SHRUBS",
    "comments": "",
    "ca_native": false,
    "origin": "",
    "fire_rating": "Fire-Prone",
    "recommendation": "Remove",
    "pyrophytic": false
  },
  {
    "scientific_name": "Chrysolepis chrysophylla",
    "common_name": "Giant Chinquapin \n(\"golden\" or \"western\")",
    "lifeform": "Shrub, Tree",
    "category": "GRASSES, GROUND COVERS & SHRUBS",
    "comments": "",
    "ca_native": true,
    "origin": "California Native",
    "fire_rating": "Fire-Prone",
    "recommendation": "Avoid",
    "pyrophytic": false
  },
  {
    "scientific_name": "Cortaderia ssp",
    "common_name": "Jubata Grass/Pampas grass",
    "lifeform": "Grass",
    "category": "GRASSES, GROUND COVERS & SHRUBS",
    "comments": "",
    "ca_native": false,
    "origin": "",
    "fire_rating": "Fire-Prone",
    "recommendation": "Remove",
    "pyrophytic": false
  },
  {
    "scientific_name": "Cytisus, Genista, Spartium",
    "common_name": "Broom - Scotch/French/Spanish",
    "lifeform": "Shrub",
    "category": "GRASSES, GROUND COVERS & SHRUBS",
    "comments": "",
    "ca_native": false,
    "origin": "",
    "fire_rating": "Fire-Prone",
    "recommendation": "Remove",
    "pyrophytic": false
  },
  {
    "scientific_name": "Dodonaea viscosa",
    "common_name": "Hopseed Bush",
    "lifeform": "Shrub",
    "category": "GRASSES, GROUND COVERS & SHRUBS",
    "comments": "",
    "ca_native": false,
    "origin": "",
    "fire_rating": "Fire-Prone",
    "recommendation": "Avoid",
    "pyrophytic": false
  },
  {
    "scientific_name": "Eriogonum fasciculatum",
    "common_name": "California Buckwheat",
    "lifeform": "Shrub",
    "category": "GRASSES, GROUND COVERS & SHRUBS",
    "comments": "",
    "ca_native": true,
    "origin": "California Native",
    "fire_rating": "Fire-Prone",
    "recommendation": "Avoid",
    "pyrophytic": false
  },
  {
    "scientific_name": "Hedera canariensis",
    "common_name": "Algerian Ivy",
    "lifeform": "Grnd cvr, Vine",
    "category": "GRASSES, GROUND COVERS & SHRUBS",
    "comments": "",
    "ca_native": false,
    "origin": "",
    "fire_rating": "Fire-Prone",
    "recommendation": "Remove",
    "pyrophytic": true
  },
  {
    "scientific_name": "Juniperus spp.",
    "common_name": "Juniper",
    "lifeform": "Shrub, Tree",
    "category": "GRASSES, GROUND COVERS & SHRUBS",
    "comments": "",
    "ca_native": false,
    "origin": "",
    "fire_rating": "Fire-Prone",
    "recommendation": "Remove",
    "pyrophytic": true
  },
  {
    "scientific_name": "Miscanthus spp.",
    "common_name": "Grasses",
    "lifeform": "Grass, perennial",
    "category": "GRASSES, GROUND COVERS & SHRUBS",
    "comments": "",
    "ca_native": false,
    "origin": "",
    "fire_rating": "Fire-Prone",
    "recommendation": "Avoid",
    "pyrophytic": false
  },
  {
    "scientific_name": "Muehlenbergia spp.",
    "common_name": "Deer Grasses",
    "lifeform": "Grass, perennial",
    "category": "GRASSES, GROUND COVERS & SHRUBS",
    "comments": "",
    "ca_native": true,
    "origin": "California Native",
    "fire_rating": "Fire-Prone",
    "recommendation": "Avoid",
    "pyrophytic": false
  },
  {
    "scientific_name": "Pennisetum spp.",
    "common_name": "Fountain Grasses",
    "lifeform": "Grass, perennial",
    "category": "GRASSES, GROUND COVERS & SHRUBS",
    "comments": "",
    "ca_native": false,
    "origin": "",
    "fire_rating": "Fire-Prone",
    "recommendation": "Remove",
    "pyrophytic": false
  },
  {
    "scientific_name": "Pickeringia montana",
    "common_name": "Chaparral Pea",
    "lifeform": "Shrub",
    "category": "GRASSES, GROUND COVERS & SHRUBS",
    "comments": "",
    "ca_native": true,
    "origin": "California Native",
    "fire_rating": "Fire-Prone",
    "recommendation": "Avoid",
    "pyrophytic": false
  },
  {
    "scientific_name": "Quercus spp. (scrub, brushy)",
    "common_name": "Scrub Oak (brushy oaks)-Coastal scrub/California scrub/Leather oak/Tucker oak/Island scrub",
    "lifeform": "Shrub",
    "category": "GRASSES, GROUND COVERS & SHRUBS",
    "comments": "",
    "ca_native": true,
    "origin": "California Native",
    "fire_rating": "Fire-Prone",
    "recommendation": "Avoid",
    "pyrophytic": false
  },
  {
    "scientific_name": "Rosmarinus officinalis",
    "common_name": "Rosemary",
    "lifeform": "Shrub",
    "category": "GRASSES, GROUND COVERS & SHRUBS",
    "comments": "",
    "ca_native": false,
    "origin": "",
    "fire_rating": "Fire-Prone",
    "recommendation": "Remove",
    "pyrophytic": false
  },
  {
    "scientific_name": "Salvia melilifera",
    "common_name": "Black Sage",
    "lifeform": "Perennial",
    "category": "GRASSES, GROUND COVERS & SHRUBS",
    "comments": "",
    "ca_native": true,
    "origin": "California Native",
    "fire_rating": "Fire-Prone",
    "recommendation": "Avoid",
    "pyrophytic": false
  },
  {
    "scientific_name": "Ulex europea",
    "common_name": "Gorse",
    "lifeform": "Shrub",
    "category": "GRASSES, GROUND COVERS & SHRUBS",
    "comments": "",
    "ca_native": false,
    "origin": "",
    "fire_rating": "Fire-Prone",
    "recommendation": "Remove",
    "pyrophytic": false
  },
  {
    "scientific_name": "Vaccinium ovatum",
    "common_name": "Evergreen Huckleberry",
    "lifeform": "Shrub",
    "category": "GRASSES, GROUND COVERS & SHRUBS",
    "comments": "",
    "ca_native": true,
    "origin": "California Native",
    "fire_rating": "Fire-Prone",
    "recommendation": "Avoid",
    "pyrophytic": false
  },
  {
    "scientific_name": "Abies spp.",
    "common_name": "Fir",
    "lifeform": "Tree",
    "category": "TREES",
    "comments": "",
    "ca_native": false,
    "origin": "",
    "fire_rating": "Fire-Prone",
    "recommendation": "Remove",
    "pyrophytic": false
  },
  {
    "scientific_name": "Acacia spp.",
    "common_name": "Acacia",
    "lifeform": "Tree",
    "category": "TREES",
    "comments": "",
    "ca_native": false,
    "origin": "",
    "fire_rating": "Fire-Prone",
    "recommendation": "Remove",
    "pyrophytic": false
  },
  {
    "scientific_name": "Cedrus spp.",
    "common_name": "Cedar",
    "lifeform": "Tree",
    "category": "TREES",
    "comments": "",
    "ca_native": false,
    "origin": "",
    "fire_rating": "Fire-Prone",
    "recommendation": "Avoid",
    "pyrophytic": false
  },
  {
    "scientific_name": "Chamaecyparis spp. (except dwarf)",
    "common_name": "False Cypress \n(Port Orford Cedar)",
    "lifeform": "Tree",
    "category": "TREES",
    "comments": "",
    "ca_native": true,
    "origin": "California Native",
    "fire_rating": "Fire-Prone",
    "recommendation": "Avoid",
    "pyrophytic": false
  },
  {
    "scientific_name": "Cryptomaria japonica \n(except dwarf)",
    "common_name": "Cryptomeria",
    "lifeform": "Tree",
    "category": "TREES",
    "comments": "",
    "ca_native": false,
    "origin": "",
    "fire_rating": "Fire-Prone",
    "recommendation": "Remove",
    "pyrophytic": false
  },
  {
    "scientific_name": "Cupressus spp.",
    "common_name": "Cypress",
    "lifeform": "Tree",
    "category": "TREES",
    "comments": "",
    "ca_native": true,
    "origin": "California Native",
    "fire_rating": "Fire-Prone",
    "recommendation": "Remove",
    "pyrophytic": false
  },
  {
    "scientific_name": "Eucalyptus ssp.",
    "common_name": "Eucalyptus - Blue/Manna/Sugar",
    "lifeform": "Tree",
    "category": "TREES",
    "comments": "",
    "ca_native": false,
    "origin": "",
    "fire_rating": "Fire-Prone",
    "recommendation": "Remove",
    "pyrophytic": false
  },
  {
    "scientific_name": "Larix spp.",
    "common_name": "Larch",
    "lifeform": "Tree",
    "category": "TREES",
    "comments": "",
    "ca_native": false,
    "origin": "",
    "fire_rating": "Fire-Prone",
    "recommendation": "Avoid",
    "pyrophytic": true
  },
  {
    "scientific_name": "Notholithocarpus densiflorus",
    "common_name": "Tan Oak, Tanbark Oak",
    "lifeform": "Tree",
    "category": "TREES",
    "comments": "",
    "ca_native": true,
    "origin": "California Native",
    "fire_rating": "Fire-Prone",
    "recommendation": "Remove",
    "pyrophytic": false
  },
  {
    "scientific_name": "Palms (if fronds left untrimmed)",
    "common_name": "Palm (if dry fronds)",
    "lifeform": "Tree",
    "category": "TREES",
    "comments": "",
    "ca_native": false,
    "origin": "",
    "fire_rating": "Fire-Prone",
    "recommendation": "Avoid",
    "pyrophytic": false
  },
  {
    "scientific_name": "Picea spp.",
    "common_name": "Spruce",
    "lifeform": "Tree",
    "category": "TREES",
    "comments": "",
    "ca_native": true,
    "origin": "California Native",
    "fire_rating": "Fire-Prone",
    "recommendation": "Remove",
    "pyrophytic": true
  },
  {
    "scientific_name": "Pinus spp.",
    "common_name": "Pine- Monterey/Bishop/Coulter/Gray/Knobcone/Pond/Scots/Torrey",
    "lifeform": "Tree",
    "category": "TREES",
    "comments": "",
    "ca_native": false,
    "origin": "",
    "fire_rating": "Fire-Prone",
    "recommendation": "Remove",
    "pyrophytic": false
  },
  {
    "scientific_name": "Pseudotsuga menziesii",
    "common_name": "Douglas Fir",
    "lifeform": "Tree",
    "category": "TREES",
    "comments": "",
    "ca_native": true,
    "origin": "California Native",
    "fire_rating": "Fire-Prone",
    "recommendation": "Avoid",
    "pyrophytic": false
  },
  {
    "scientific_name": "Schinus spp.",
    "common_name": "Pepper Tree",
    "lifeform": "Tree",
    "category": "TREES",
    "comments": "",
    "ca_native": false,
    "origin": "",
    "fire_rating": "Fire-Prone",
    "recommendation": "Remove",
    "pyrophytic": true
  },
  {
    "scientific_name": "Tamarix spp.",
    "common_name": "Tamarisk, Salt Cedar",
    "lifeform": "Tree",
    "category": "TREES",
    "comments": "",
    "ca_native": false,
    "origin": "",
    "fire_rating": "Fire-Prone",
    "recommendation": "Remove",
    "pyrophytic": false
  },
  {
    "scientific_name": "Taxus spp. (except dwarf)",
    "common_name": "Yew",
    "lifeform": "Tree",
    "category": "TREES",
    "comments": "",
    "ca_native": false,
    "origin": "",
    "fire_rating": "Fire-Prone",
    "recommendation": "Avoid",
    "pyrophytic": false
  },
  {
    "scientific_name": "Thuja spp.",
    "common_name": "American Arborvitae/\nWestern Red Cedar",
    "lifeform": "Tree",
    "category": "TREES",
    "comments": "",
    "ca_native": false,
    "origin": "",
    "fire_rating": "Fire-Prone",
    "recommendation": "Remove",
    "pyrophytic": false
  },
  {
    "scientific_name": "Toxodium spp.",
    "common_name": "Bald Cypress",
    "lifeform": "Tree",
    "category": "TREES",
    "comments": "",
    "ca_native": false,
    "origin": "",
    "fire_rating": "Fire-Prone",
    "recommendation": "Remove",
    "pyrophytic": true
  },
  {
    "scientific_name": "Tsuga spp.",
    "common_name": "Hemlock",
    "lifeform": "Tree",
    "category": "TREES",
    "comments": "",
    "ca_native": false,
    "origin": "",
    "fire_rating": "Fire-Prone",
    "recommendation": "Remove",
    "pyrophytic": false
  },
  {
    "scientific_name": "Umbellularia californica",
    "common_name": "California Bay",
    "lifeform": "Tree",
    "category": "TREES",
    "comments": "",
    "ca_native": true,
    "origin": "California Native",
    "fire_rating": "Fire-Prone",
    "recommendation": "Remove",
    "pyrophytic": false
  },
  {
    "scientific_name": "Lonicera japonica",
    "common_name": "Japanese honeysuckle",
    "lifeform": "Vine",
    "category": "VINES",
    "comments": "",
    "ca_native": false,
    "origin": "",
    "fire_rating": "Fire-Prone",
    "recommendation": "Remove",
    "pyrophytic": false
  }
]